odoo/addons/sale_stock_operating_unit/README.rst
odoo/addons/sale_stock_operating_unit/__init__.py
odoo/addons/sale_stock_operating_unit/__manifest__.py
odoo/addons/sale_stock_operating_unit/i18n/es.po
odoo/addons/sale_stock_operating_unit/i18n/it.po
odoo/addons/sale_stock_operating_unit/i18n/pt.po
odoo/addons/sale_stock_operating_unit/i18n/sale_stock_operating_unit.pot
odoo/addons/sale_stock_operating_unit/models/__init__.py
odoo/addons/sale_stock_operating_unit/models/sale_order.py
odoo/addons/sale_stock_operating_unit/models/stock_move.py
odoo/addons/sale_stock_operating_unit/models/stock_warehouse.py
odoo/addons/sale_stock_operating_unit/readme/CONTRIBUTORS.rst
odoo/addons/sale_stock_operating_unit/readme/DESCRIPTION.rst
odoo/addons/sale_stock_operating_unit/readme/USAGE.rst
odoo/addons/sale_stock_operating_unit/static/description/icon.png
odoo/addons/sale_stock_operating_unit/static/description/index.html
odoo/addons/sale_stock_operating_unit/tests/__init__.py
odoo/addons/sale_stock_operating_unit/tests/test_sale_stock_operating_unit.py
odoo14_addon_sale_stock_operating_unit-14.0.1.0.1.dev7.dist-info/METADATA
odoo14_addon_sale_stock_operating_unit-14.0.1.0.1.dev7.dist-info/WHEEL
odoo14_addon_sale_stock_operating_unit-14.0.1.0.1.dev7.dist-info/top_level.txt
odoo14_addon_sale_stock_operating_unit-14.0.1.0.1.dev7.dist-info/RECORD
