Metadata-Version: 2.1
Name: odoo14-addon-sale-stock-operating-unit
Version: 14.0.1.0.1.dev7
Summary: An operating unit (OU) is an organizational entity part of a company
Home-page: https://github.com/OCA/operating-unit
Author: ForgeFlow, Serpent Consulting Services Pvt. Ltd., Odoo Community Association (OCA)
Author-email: support@odoo-community.org
License: LGPL-3
Platform: UNKNOWN
Classifier: Programming Language :: Python
Classifier: Framework :: Odoo
Classifier: Framework :: Odoo :: 14.0
Classifier: License :: OSI Approved :: GNU Lesser General Public License v3 (LGPLv3)
Requires-Python: >=3.6
Requires-Dist: odoo14-addon-sale-operating-unit
Requires-Dist: odoo14-addon-stock-operating-unit
Requires-Dist: odoo <14.1dev,>=14.0a
